colab_load/__init__.py
colab_load/check_func.py
colab_load/load.py
colab_load/take_file.py
colab_load-1.0.4.dist-info/METADATA
colab_load-1.0.4.dist-info/WHEEL
colab_load-1.0.4.dist-info/top_level.txt
colab_load-1.0.4.dist-info/RECORD
